AUTHORS
Changelog
INSTALL
LICENSE
MANIFEST.in
README
README.rst
TODO
setup.py
bundle/__init__.py
bundle/bundles.py
bundle/extensions.py
bundle/setup.py
bundle/utils.py
bundle/versions.py
bundle.egg-info/PKG-INFO
bundle.egg-info/SOURCES.txt
bundle.egg-info/dependency_links.txt
bundle.egg-info/entry_points.txt
bundle.egg-info/not-zip-safe
bundle.egg-info/requires.txt
bundle.egg-info/top_level.txt
bundle/files/README.t
bundle/files/__init__.py
bundle/files/setup.py.t
requirements/default.txt