Metadata-Version: 1.0
Name: bundle
Version: 1.1.1
Summary: Create and manage bundle packages.
Home-page: http://github.com/ask/bundle/
Author: Ask Solem
Author-email: ask@celeryproject.org
License: UNKNOWN
Platform: any
Classifier: Development Status :: 4 - Beta
Classifier: License :: OSI Approved :: BSD License
Classifier: Operating System :: OS Independent
Classifier: Programming Language :: Python
Classifier: Programming Language :: Python :: 3
Classifier: Programming Language :: Python :: 2.7
Classifier: Programming Language :: Python :: 2.6
Classifier: Programming Language :: Python :: 2.5
Classifier: Programming Language :: Python :: 2
Classifier: Intended Audience :: Developers
Classifier: Topic :: System :: Software Distribution
Classifier: Topic :: System :: Installation/Setup
Classifier: Topic :: Software Development :: Libraries :: Python Modules
Classifier: Framework :: Setuptools Plugin
